{
  "last_update_utc": "2026-04-22T14:13:51.310395+00:00",
  "symbol": "NQ=F",
  "session": "ny_open",
  "market_state": "bull_trend",
  "price": 26886.25,
  "regime_5m": "bull",
  "confidence_5m": 3,
  "regime_1h": "bull",
  "confidence_1h": 3,
  "regime_4h": "bull",
  "confidence_4h": 3,
  "rsi": 61.0169,
  "atr": 38.5179,
  "ema9": 26859.0367,
  "ema21": 26852.2653,
  "ema50": 26844.5114,
  "close_vs_ema21_atr": 0.8823,
  "range_pct_atr": 1.045,
  "active_models": [
    "aggr_pullback",
    "ifvg_long"
  ]
}
