{
  "last_update_utc": "2026-04-22T12:59:47.292450+00:00",
  "symbol": "NQ=F",
  "session": "off_hours",
  "market_state": "bull_pullback",
  "price": 26827.5,
  "regime_5m": "chop",
  "confidence_5m": 0,
  "regime_1h": "bull",
  "confidence_1h": 3,
  "regime_4h": "bull",
  "confidence_4h": 3,
  "rsi": 52.2989,
  "atr": 22.3214,
  "ema9": 26851.9436,
  "ema21": 26847.663,
  "ema50": 26839.1644,
  "close_vs_ema21_atr": -0.9033,
  "range_pct_atr": 1.3776,
  "active_models": [
    "aggr_pullback",
    "ifvg_long"
  ]
}
