{
  "last_update_utc": "2026-04-22T14:52:19.756527+00:00",
  "symbol": "NQ=F",
  "session": "ny_open",
  "market_state": "overextended_bull",
  "price": 26985.25,
  "regime_5m": "bull",
  "confidence_5m": 3,
  "regime_1h": "bull",
  "confidence_1h": 3,
  "regime_4h": "bull",
  "confidence_4h": 3,
  "rsi": 80.9249,
  "atr": 40.25,
  "ema9": 26952.3362,
  "ema21": 26911.8676,
  "ema50": 26876.2464,
  "close_vs_ema21_atr": 1.8232,
  "range_pct_atr": 0.7143,
  "active_models": [
    "aggr_pullback",
    "ifvg_long"
  ]
}
