{
  "last_update_utc": "2026-04-22T14:56:47.406419+00:00",
  "symbol": "NQ=F",
  "session": "ny_open",
  "market_state": "overextended_bull",
  "price": 26980.75,
  "regime_5m": "bull",
  "confidence_5m": 3,
  "regime_1h": "bull",
  "confidence_1h": 3,
  "regime_4h": "bull",
  "confidence_4h": 3,
  "rsi": 76.4388,
  "atr": 40.3036,
  "ema9": 26955.4589,
  "ema21": 26916.8073,
  "ema50": 26879.7417,
  "close_vs_ema21_atr": 1.5865,
  "range_pct_atr": 0.4528,
  "active_models": [
    "aggr_pullback",
    "ifvg_long"
  ]
}
